ya_market/__init__.py
ya_market/api_client.py
ya_market/configuration.py
ya_market/exceptions.py
ya_market/rest.py
ya_market/api/__init__.py
ya_market/api/provider_api.py
ya_market/api/requestor_api.py
ya_market/models/__init__.py
ya_market/models/agreement.py
ya_market/models/agreement_event.py
ya_market/models/agreement_event_all_of.py
ya_market/models/agreement_proposal.py
ya_market/models/demand.py
ya_market/models/demand_all_of.py
ya_market/models/demand_offer_base.py
ya_market/models/error_message.py
ya_market/models/event.py
ya_market/models/offer.py
ya_market/models/offer_all_of.py
ya_market/models/property_query.py
ya_market/models/property_query_event.py
ya_market/models/property_query_event_all_of.py
ya_market/models/proposal.py
ya_market/models/proposal_all_of.py
ya_market/models/proposal_event.py
ya_market/models/proposal_event_all_of.py
ya_market-0.1.0.dist-info/DESCRIPTION.rst
ya_market-0.1.0.dist-info/METADATA
ya_market-0.1.0.dist-info/RECORD
ya_market-0.1.0.dist-info/WHEEL
ya_market-0.1.0.dist-info/metadata.json
ya_market-0.1.0.dist-info/top_level.txt
