Metadata-Version: 2.0
Name: ya-market
Version: 0.1.0
Summary: Yagna Market API
Home-page: UNKNOWN
Author: OpenAPI Generator community
Author-email: team@openapitools.org
License: UNKNOWN
Keywords: OpenAPI,OpenAPI-Generator,Yagna Market API
Platform: UNKNOWN
Requires-Dist: aiohttp (>=3.0.0)
Requires-Dist: certifi
Requires-Dist: python-dateutil
Requires-Dist: six (>=1.10)
Requires-Dist: urllib3 (>=1.15)
